django_ledger/__init__.py
django_ledger/apps.py
django_ledger/context.py
django_ledger/exceptions.py
django_ledger/settings.py
django_ledger/utils.py
django_ledger/admin/__init__.py
django_ledger/admin/chart_of_accounts.py
django_ledger/admin/entity.py
django_ledger/admin/ledger.py
django_ledger/contrib/__init__.py
django_ledger/forms/__init__.py
django_ledger/forms/account.py
django_ledger/forms/app_filters.py
django_ledger/forms/auth.py
django_ledger/forms/bank_account.py
django_ledger/forms/bill.py
django_ledger/forms/chart_of_accounts.py
django_ledger/forms/closing_entry.py
django_ledger/forms/customer.py
django_ledger/forms/data_import.py
django_ledger/forms/entity.py
django_ledger/forms/estimate.py
django_ledger/forms/feedback.py
django_ledger/forms/invoice.py
django_ledger/forms/item.py
django_ledger/forms/journal_entry.py
django_ledger/forms/ledger.py
django_ledger/forms/purchase_order.py
django_ledger/forms/transactions.py
django_ledger/forms/unit.py
django_ledger/forms/utils.py
django_ledger/forms/vendor.py
django_ledger/io/__init__.py
django_ledger/io/io_context.py
django_ledger/io/io_core.py
django_ledger/io/io_generator.py
django_ledger/io/io_library.py
django_ledger/io/io_middleware.py
django_ledger/io/ofx.py
django_ledger/io/ratios.py
django_ledger/io/roles.py
django_ledger/management/__init__.py
django_ledger/management/commands/__init__.py
django_ledger/management/commands/generate_oauth2_codes.py
django_ledger/migrations/0001_initial.py
django_ledger/migrations/0002_alter_journalentrymodel_managers_and_more.py
django_ledger/migrations/0003_remove_accountmodel_django_ledg_role_1bff96_idx_and_more.py
django_ledger/migrations/0004_remove_itemmodel_depth_remove_itemmodel_numchild_and_more.py
django_ledger/migrations/0005_remove_itemmodel_django_ledg_invento_dbf206_idx_and_more.py
django_ledger/migrations/0006_alter_journalentrymodel_je_number_and_more.py
django_ledger/migrations/0007_remove_customermodel_django_ledg_custome_16f95a_idx_and_more.py
django_ledger-0.8.3.dist-info/licenses/AUTHORS.md
django_ledger-0.8.3.dist-info/licenses/LICENSE
django_ledger-0.8.3.dist-info/METADATA
django_ledger-0.8.3.dist-info/WHEEL
django_ledger-0.8.3.dist-info/top_level.txt
django_ledger-0.8.3.dist-info/RECORD
