Metadata-Version: 2.4
Name: django-ledger
Version: 0.8.3
Summary: Double entry accounting system built on the Django Web Framework.
Author-email: Miguel Sanda <msanda@arrobalytics.com>
Maintainer-email: Miguel Sanda <msanda@arrobalytics.com>
License: GPLv3 License
Project-URL: Homepage, https://www.djangoledger.com
Project-URL: Bug Tracker, https://github.com/arrobalytics/django-ledger/issues
Project-URL: Documentation, https://django-ledger.readthedocs.io/en/latest/
Project-URL: Source Code, https://github.com/arrobalytics/django-ledger
Keywords: django,finance,bookkeeping,accounting,balance sheet,income statement,general ledger,money,engine
Classifier: Programming Language :: Python :: 3
Classifier: Programming Language :: Python :: Implementation :: CPython
Classifier: Topic :: Office/Business :: Financial :: Accounting
Classifier: Framework :: Django :: 4.0
Classifier: Framework :: Django :: 5.0
Classifier: Intended Audience :: Financial and Insurance Industry
Classifier: Intended Audience :: End Users/Desktop
Classifier: License :: OSI Approved :: GNU General Public License v3 or later (GPLv3+)
Requires-Python: >=3.11
License-File: LICENSE
License-File: AUTHORS.md
Requires-Dist: django>=4.2
Requires-Dist: django-treebeard>=4.7.1
Requires-Dist: faker>=37.6.0
Requires-Dist: fpdf2>=2.8.4
Requires-Dist: markdown>=3.9
Requires-Dist: ofxtools>=0.9.5
Requires-Dist: pillow>=11.3.0
Dynamic: license-file
